evlog.py
evlog-0.1.7.dist-info/METADATA
evlog-0.1.7.dist-info/WHEEL
evlog-0.1.7.dist-info/entry_points.txt
evlog-0.1.7.dist-info/licenses/LICENSE
evlog-0.1.7.dist-info/RECORD
