Metadata-Version: 2.4
Name: evlog
Version: 0.1.7
Summary: A utility for logging daily events and tasks.
Project-URL: Homepage, https://git.hyperreal.coffee/hyperreal/evlog
Project-URL: Issues, https://git.hyperreal.coffee/hyperreal/evlog/issues
Author-email: Jeffrey Serio <hyperreal@moonshadow.dev>
License-File: LICENSE
Requires-Python: >=3.10
Requires-Dist: jsonschema>=4.17.0
Requires-Dist: rich>=12.6.0
